fio_banka.py
fio_banka-3.0.1.dist-info/LICENSE
fio_banka-3.0.1.dist-info/METADATA
fio_banka-3.0.1.dist-info/WHEEL
fio_banka-3.0.1.dist-info/top_level.txt
fio_banka-3.0.1.dist-info/RECORD
