Metadata-Version: 2.1
Name: fio_banka
Version: 3.0.1
Summary: Fio Banka API
Author-email: Petr Beranek <petrberanek.mail@gmail.com>
License: MIT License
Project-URL: Homepage, https://github.com/peberanek/fio-banka
Keywords: finance,fio,bank,api,czech
Classifier: Development Status :: 5 - Production/Stable
Classifier: Intended Audience :: Developers
Classifier: Intended Audience :: Financial and Insurance Industry
Classifier: Programming Language :: Python :: 3.11
Classifier: Programming Language :: Python :: 3.12
Classifier: License :: OSI Approved :: MIT License
Classifier: Topic :: Communications
Classifier: Topic :: Office/Business :: Financial
Requires-Python: >=3.11
License-File: LICENSE
Requires-Dist: requests ~=2.31
